aimet/__init__.py
aimet/src/__init__.py
aimet/src/describe.py
aimet/test/__init__.py
aimet/test/test_aimet.py
aimet-0.0.1.dist-info/LICENSE
aimet-0.0.1.dist-info/METADATA
aimet-0.0.1.dist-info/WHEEL
aimet-0.0.1.dist-info/top_level.txt
aimet-0.0.1.dist-info/RECORD
